torchzoo/__init__.py
torchzoo/rnn.py
torchzoo/simple.py
torchzoo-0.24.dist-info/METADATA
torchzoo-0.24.dist-info/RECORD
torchzoo-0.24.dist-info/WHEEL
torchzoo-0.24.dist-info/top_level.txt
