Metadata-Version: 2.1
Name: torchzoo
Version: 0.24
Summary: Various Implementations of neural models defined in papers
Home-page: http://gitlab.com/theSage21/torchzoo
Author: Arjoonn Sharma
Author-email: arjoonn.94@gmail.com
License: UNKNOWN
Keywords: torchzoo,pytorch,paper implementation
Platform: UNKNOWN
